{
 "key": "childsplay-2019",
 "title": "Child’s Play",
 "year": 2019,
 "movie_url": "/movie/Childs-Play-(2019)",
 "opening_date": "2019-06-21",
 "opening_gross": 14094594,
 "weekends": [
  {
   "n": 1,
   "date": "2019-06-21",
   "gross": 14094594,
   "rank": 2,
   "theaters": 3007,
   "total_gross": 14094594
  },
  {
   "n": 2,
   "date": "2019-06-28",
   "gross": 4429543,
   "rank": 8,
   "theaters": 3007,
   "total_gross": 23557942
  },
  {
   "n": 3,
   "date": "2019-07-05",
   "gross": 1492831,
   "rank": 12,
   "theaters": 1707,
   "total_gross": 26854570
  },
  {
   "n": 4,
   "date": "2019-07-12",
   "gross": 590970,
   "rank": 15,
   "theaters": 807,
   "total_gross": 28416486
  },
  {
   "n": 5,
   "date": "2019-07-19",
   "gross": 122937,
   "rank": 28,
   "theaters": 207,
   "total_gross": 28881279
  },
  {
   "n": 6,
   "date": "2019-07-26",
   "gross": 89761,
   "rank": 29,
   "theaters": 125,
   "total_gross": 29063266
  },
  {
   "n": 7,
   "date": "2019-08-02",
   "gross": 57227,
   "rank": 30,
   "theaters": 90,
   "total_gross": 29176532
  }
 ]
}