{
 "key": "comeandsee1987rerelease",
 "title": "Come and See (1987) (Re-Release)",
 "year": null,
 "movie_url": "/movie/Come-and-See",
 "opening_date": "2020-02-21",
 "opening_gross": 16053,
 "weekends": [
  {
   "n": 1,
   "date": "2020-02-21",
   "gross": 16053,
   "rank": 51,
   "theaters": 1,
   "total_gross": 16053
  },
  {
   "n": 2,
   "date": "2020-02-28",
   "gross": 12859,
   "rank": 55,
   "theaters": 1,
   "total_gross": 38012
  },
  {
   "n": 3,
   "date": "2020-03-06",
   "gross": 8157,
   "rank": 64,
   "theaters": 3,
   "total_gross": 61979
  },
  {
   "n": 4,
   "date": "2020-03-13",
   "gross": 2933,
   "rank": 60,
   "theaters": 2,
   "total_gross": 70831
  }
 ]
}