{
 "key": "dysfunktionalfamily",
 "title": "DysFunkTional Family",
 "opening_date": "2003-04-04",
 "opening_gross": 1079797,
 "weekends": [
  {
   "n": 1,
   "date": "2003-04-04",
   "gross": 1079797,
   "rank": 17,
   "theaters": 602,
   "total_gross": 0
  },
  {
   "n": 2,
   "date": "2003-04-11",
   "gross": 463379,
   "rank": 19,
   "theaters": 602,
   "total_gross": 0
  },
  {
   "n": 3,
   "date": "2003-04-18",
   "gross": 112612,
   "rank": 43,
   "theaters": 152,
   "total_gross": 0
  },
  {
   "n": 4,
   "date": "2003-04-25",
   "gross": 28697,
   "rank": 67,
   "theaters": 50,
   "total_gross": 0
  },
  {
   "n": 5,
   "date": "2003-05-02",
   "gross": 7568,
   "rank": 100,
   "theaters": 11,
   "total_gross": 0
  },
  {
   "n": 6,
   "date": "2003-05-09",
   "gross": 5068,
   "rank": 106,
   "theaters": 9,
   "total_gross": 0
  },
  {
   "n": 7,
   "date": "2003-05-16",
   "gross": 3200,
   "rank": 118,
   "theaters": 5,
   "total_gross": 0
  }
 ]
}