{
 "key": "itsadisaster",
 "title": "It's a Disaster",
 "year": null,
 "movie_url": "/movie/Its-a-Disaster",
 "opening_date": "2013-04-12",
 "opening_gross": 15305,
 "weekends": [
  {
   "n": 1,
   "date": "2013-04-12",
   "gross": 15305,
   "rank": 69,
   "theaters": 3,
   "total_gross": 15305
  },
  {
   "n": 2,
   "date": "2013-04-19",
   "gross": 18088,
   "rank": 64,
   "theaters": 13,
   "total_gross": 38100
  },
  {
   "n": 3,
   "date": "2013-04-26",
   "gross": 10500,
   "rank": 72,
   "theaters": 9,
   "total_gross": 57216
  }
 ]
}