{
 "key": "startrekfirstcontact",
 "title": "Star Trek: First Contact",
 "year": null,
 "movie_url": "/movie/Star-Trek-First-Contact",
 "opening_date": "1996-11-22",
 "opening_gross": 30716131,
 "weekends": [
  {
   "n": 1,
   "date": "1996-11-22",
   "gross": 30716131,
   "rank": 1,
   "theaters": 2812,
   "total_gross": 30716131
  },
  {
   "n": 2,
   "date": "1996-11-29",
   "gross": 25484402,
   "rank": 2,
   "theaters": 2812,
   "total_gross": 60850689
  },
  {
   "n": 3,
   "date": "1996-12-06",
   "gross": 6609903,
   "rank": 3,
   "theaters": 2812,
   "total_gross": 71146315
  },
  {
   "n": 4,
   "date": "1996-12-13",
   "gross": 3432345,
   "rank": 7,
   "theaters": 2607,
   "total_gross": 76721064
  },
  {
   "n": 5,
   "date": "1996-12-20",
   "gross": 2306509,
   "rank": 11,
   "theaters": 1569,
   "total_gross": 80389431
  },
  {
   "n": 6,
   "date": "1996-12-27",
   "gross": 2570680,
   "rank": 15,
   "theaters": 1019,
   "total_gross": 85122152
  },
  {
   "n": 7,
   "date": "1997-01-03",
   "gross": 1760201,
   "rank": 15,
   "theaters": 1001,
   "total_gross": 89128389
  },
  {
   "n": 8,
   "date": "1997-01-10",
   "gross": 587727,
   "rank": 22,
   "theaters": 607,
   "total_gross": 90147619
  },
  {
   "n": 9,
   "date": "1997-01-17",
   "gross": 383672,
   "rank": 28,
   "theaters": 383,
   "total_gross": 90688158
  },
  {
   "n": 10,
   "date": "1997-01-24",
   "gross": 140590,
   "rank": 37,
   "theaters": 328,
   "total_gross": 90891850
  },
  {
   "n": 11,
   "date": "1997-01-31",
   "gross": 98089,
   "rank": 42,
   "theaters": 243,
   "total_gross": 91033490
  },
  {
   "n": 12,
   "date": "1997-02-07",
   "gross": 44595,
   "rank": 54,
   "theaters": 142,
   "total_gross": 91103043
  },
  {
   "n": 13,
   "date": "1997-02-14",
   "gross": 323677,
   "rank": 30,
   "theaters": 508,
   "total_gross": 91438883
  },
  {
   "n": 14,
   "date": "1997-02-21",
   "gross": 139874,
   "rank": 37,
   "theaters": 308,
   "total_gross": 91658242
  },
  {
   "n": 15,
   "date": "1997-02-28",
   "gross": 100629,
   "rank": 39,
   "theaters": 232,
   "total_gross": 91798391
  },
  {
   "n": 16,
   "date": "1997-03-07",
   "gross": 64872,
   "rank": 45,
   "theaters": 153,
   "total_gross": 91898902
  },
  {
   "n": 17,
   "date": "1997-03-14",
   "gross": 42987,
   "rank": 50,
   "theaters": 95,
   "total_gross": 91968563
  }
 ]
}