{
 "key": "thefiveyearengagement",
 "title": "The Five-Year Engagement",
 "opening_date": "2012-04-27",
 "opening_gross": 10610060,
 "weekends": [
  {
   "n": 1,
   "date": "2012-04-27",
   "gross": 10610060,
   "rank": 5,
   "theaters": 2936,
   "total_gross": 0
  },
  {
   "n": 2,
   "date": "2012-05-04",
   "gross": 5029110,
   "rank": 6,
   "theaters": 2941,
   "total_gross": 0
  },
  {
   "n": 3,
   "date": "2012-05-11",
   "gross": 3314010,
   "rank": 6,
   "theaters": 2569,
   "total_gross": 0
  },
  {
   "n": 4,
   "date": "2012-05-18",
   "gross": 1110375,
   "rank": 11,
   "theaters": 1175,
   "total_gross": 0
  },
  {
   "n": 5,
   "date": "2012-05-25",
   "gross": 294555,
   "rank": 19,
   "theaters": 274,
   "total_gross": 0
  },
  {
   "n": 6,
   "date": "2012-06-01",
   "gross": 179845,
   "rank": 25,
   "theaters": 218,
   "total_gross": 0
  },
  {
   "n": 7,
   "date": "2012-06-08",
   "gross": 121625,
   "rank": 28,
   "theaters": 175,
   "total_gross": 0
  },
  {
   "n": 8,
   "date": "2012-06-15",
   "gross": 92440,
   "rank": 32,
   "theaters": 168,
   "total_gross": 0
  }
 ]
}