{
 "key": "themortuaryassistant-2026",
 "title": "The Mortuary Assistant",
 "year": 2026,
 "movie_url": "/movie/Mortuary-Assistant-The-(2026)",
 "opening_date": "2026-02-13",
 "opening_gross": 259338,
 "weekends": [
  {
   "n": 1,
   "date": "2026-02-13",
   "gross": 259338,
   "rank": 24,
   "theaters": 208,
   "total_gross": 259338
  },
  {
   "n": 2,
   "date": "2026-02-20",
   "gross": 73532,
   "rank": 33,
   "theaters": 148,
   "total_gross": 406309
  },
  {
   "n": 3,
   "date": "2026-02-27",
   "gross": 12807,
   "rank": 48,
   "theaters": 32,
   "total_gross": 449819
  }
 ]
}