{
 "key": "thestepfather-2009",
 "title": "The Stepfather",
 "year": 2009,
 "movie_url": "/movie/Stepfather-The-(2009)",
 "opening_date": "2009-10-16",
 "opening_gross": 11581586,
 "weekends": [
  {
   "n": 1,
   "date": "2009-10-16",
   "gross": 11581586,
   "rank": 5,
   "theaters": 2734,
   "total_gross": 11581586
  },
  {
   "n": 2,
   "date": "2009-10-23",
   "gross": 6230969,
   "rank": 8,
   "theaters": 2734,
   "total_gross": 20082652
  },
  {
   "n": 3,
   "date": "2009-10-30",
   "gross": 3207792,
   "rank": 8,
   "theaters": 2346,
   "total_gross": 24555801
  },
  {
   "n": 4,
   "date": "2009-11-06",
   "gross": 1800133,
   "rank": 14,
   "theaters": 1424,
   "total_gross": 27415203
  },
  {
   "n": 5,
   "date": "2009-11-13",
   "gross": 836327,
   "rank": 16,
   "theaters": 858,
   "total_gross": 28802131
  },
  {
   "n": 6,
   "date": "2009-11-20",
   "gross": 101187,
   "rank": 31,
   "theaters": 191,
   "total_gross": 29062561
  }
 ]
}