{
  "tmdb_id": 102821,
  "title": "Home Road Movies",
  "tagline": "",
  "overview": "A sweet reminiscence about a family of four children and their RAF-veteran dad, who knows the timetable of every bus in London, but realizes his large family needs a car. He buys a Peugeot station wagon - license plate GFP831E, and the family sets off for annual holidays exploring every corner of Europe - \"adopting local customs but never forgetting who won the war.\" The narrator is one of the children who, as he ages, sees things he missed as a lad - the car no rocket, dad no speedster. As the years wear on, and the car sits in the driveway, dad keeps it ready for the next great summer holiday.",
  "release_date": "2002-06-07",
  "runtime": 12,
  "budget": 0,
  "revenue": 0,
  "genres": [
    "Animation",
    "Drama"
  ],
  "mpaa": "",
  "poster_url": "",
  "backdrop_url": "",
  "director": "Robert Bradbrook",
  "cast": [
    {
      "name": "Bill Paterson",
      "character": "Father",
      "profile": "https://image.tmdb.org/t/p/w185/mk5vpYLmER7asqOhEwVKXD3P3YE.jpg"
    },
    {
      "name": "Phelim McDermott",
      "character": "Narrator (voice)",
      "profile": "https://image.tmdb.org/t/p/w185/9jxA0ZUS0HvaTKkrNrSpU3UxITE.jpg"
    },
    {
      "name": "Amal Anwar",
      "character": "Child (voice)",
      "profile": ""
    },
    {
      "name": "Joseph Arieli-Edwards",
      "character": "Child (voice)",
      "profile": ""
    },
    {
      "name": "Tom Eilenberg",
      "character": "Child (voice)",
      "profile": ""
    },
    {
      "name": "Rob Robinson",
      "character": "Child (voice)",
      "profile": ""
    },
    {
      "name": "Gem Souleyman",
      "character": "Child (voice)",
      "profile": ""
    }
  ],
  "trailer_key": null,
  "imdb_id": "tt0308376",
  "vote_average": 6.4,
  "vote_count": 5
}