{
  "tmdb_id": 1138343,
  "title": "Allegiance: ....time to react LIVE!",
  "tagline": "",
  "overview": "Time To React - Live! is the first live album by Australian Thrash metal band Allegiance, released in 1995. The album was recorded live at Triple J Studios in Perth, Western Australia on 17 December 1994  Intro  Chaos Dies\r Pity\r Trapped Behind A Shadow\r Hate Frenzy\r Time To React\r Taken By Force\r Torn Between Two Worlds\r One Step Beyond\r Downward Spiral",
  "release_date": "1995-01-01",
  "runtime": 49,
  "budget": 0,
  "revenue": 0,
  "genres": [
    "Music"
  ],
  "mpaa": "",
  "poster_url": "https://image.tmdb.org/t/p/w342/iwiwQIewtYbR8hlVAfFjSlslOCa.jpg",
  "backdrop_url": "",
  "director": "",
  "cast": [],
  "trailer_key": null,
  "imdb_id": null,
  "vote_average": 0.0,
  "vote_count": 0
}