{
  "tmdb_id": 13569,
  "title": "Thr3e",
  "tagline": "",
  "overview": "Innocent lives hang on the whim of an elusive psychopathic murderer whose strange riddles and impossible timelines force three people into a mission to end the game before one or all of them die.",
  "release_date": "2007-01-05",
  "runtime": 101,
  "budget": 2400000,
  "revenue": 0,
  "genres": [
    "Horror",
    "Thriller"
  ],
  "mpaa": "PG-13",
  "poster_url": "https://image.tmdb.org/t/p/w342/fGXWsdhfJ4UIdCnsCJMkT2Ulo9p.jpg",
  "backdrop_url": "https://image.tmdb.org/t/p/w1280/d4dkc0QhuEv1tRtqtaFzijky0OD.jpg",
  "director": "Robby Henson",
  "cast": [
    {
      "name": "Marc Blucas",
      "character": "Kevin Parson",
      "profile": "https://image.tmdb.org/t/p/w185/zQrZosMrd5pDWTaoOIHcbfeFOQS.jpg"
    },
    {
      "name": "Justine Waddell",
      "character": "Jennifer Peters",
      "profile": "https://image.tmdb.org/t/p/w185/gVPTeUJW1Doq19LTPZfsfNqC06N.jpg"
    },
    {
      "name": "Bill Moseley",
      "character": "Slater",
      "profile": "https://image.tmdb.org/t/p/w185/tRyt4wTgNYJl7eqhM56B3gukU2A.jpg"
    },
    {
      "name": "Priscilla Barnes",
      "character": "Balinda Parson",
      "profile": "https://image.tmdb.org/t/p/w185/3bEvjncb05fI7dIwzjeUrvc54qA.jpg"
    },
    {
      "name": "Jack Ryan",
      "character": "Slater - young",
      "profile": "https://image.tmdb.org/t/p/w185/6gvdjFEhK1x7L5E4CjqU7fonnHc.jpg"
    },
    {
      "name": "Kevin Downes",
      "character": "Henry",
      "profile": "https://image.tmdb.org/t/p/w185/nrCeOB2G2AmZrvMqWUHzKGAiqv4.jpg"
    },
    {
      "name": "Alanna Bale",
      "character": "Young Samantha",
      "profile": "https://image.tmdb.org/t/p/w185/oxVqYekCKLpAPgU34YXCpLLHe0R.jpg"
    },
    {
      "name": "Laura Jordan",
      "character": "Samantha Sheer",
      "profile": "https://image.tmdb.org/t/p/w185/9gBuEHbnoPSqlm3CrdqPcLucQQd.jpg"
    },
    {
      "name": "Max Ryan",
      "character": "Captain Milton",
      "profile": "https://image.tmdb.org/t/p/w185/q21XcN0YzA7lDHuFbwGAV9O6N9J.jpg"
    },
    {
      "name": "Kai Schoenhals",
      "character": "Hot Dog Vendor",
      "profile": ""
    }
  ],
  "trailer_key": "mdOFvLZx-Ho",
  "imdb_id": "tt0486028",
  "vote_average": 5.118,
  "vote_count": 93
}