{
  "tmdb_id": 25059,
  "title": "Homeward Bound II: Lost in San Francisco",
  "tagline": "Your favorite talking animals are back!",
  "overview": "When the pets accidentally get separated from their vacationing owners, Chance, Shadow, and Sassy navigate the mean streets of San Francisco, trying to find their home across the Golden Gate Bridge. But the road is blocked by a series of hazards, both man and beast.",
  "release_date": "1996-03-08",
  "runtime": 89,
  "budget": 0,
  "revenue": 32709423,
  "genres": [
    "Adventure",
    "Comedy",
    "Drama",
    "Family"
  ],
  "mpaa": "G",
  "poster_url": "https://image.tmdb.org/t/p/w342/kfYawa9SF9MQ3ae0TXAfhDLFGv7.jpg",
  "backdrop_url": "https://image.tmdb.org/t/p/w1280/sMukEdOweNU9UveS1FPTnzVpB9p.jpg",
  "director": "David R. Ellis",
  "cast": [
    {
      "name": "Michael J. Fox",
      "character": "Chance (voice)",
      "profile": "https://image.tmdb.org/t/p/w185/2JB4FMgQmnhbBlQ4SxWFN9EIVDi.jpg"
    },
    {
      "name": "Sally Field",
      "character": "Sassy (voice)",
      "profile": "https://image.tmdb.org/t/p/w185/iMeq1j9Xwvaf6PbTJ0FQz69fpuA.jpg"
    },
    {
      "name": "Ralph Waite",
      "character": "Shadow (voice)",
      "profile": "https://image.tmdb.org/t/p/w185/9piV2h6tAuhynRP0PSmM2IsSh69.jpg"
    },
    {
      "name": "Robert Hays",
      "character": "Bob Seaver",
      "profile": "https://image.tmdb.org/t/p/w185/pqu0hSAdHGItjP0iqkbTg4Ocv9w.jpg"
    },
    {
      "name": "Kim Greist",
      "character": "Laura Burnford-Seaver",
      "profile": "https://image.tmdb.org/t/p/w185/zYMORBHyCcXbbchiKGhhrnJyoix.jpg"
    },
    {
      "name": "Michael Bell",
      "character": "Stokey (voice)",
      "profile": "https://image.tmdb.org/t/p/w185/qZrtEHcKOFCbxtSedcdTU8f2uyW.jpg"
    },
    {
      "name": "Tisha Campbell",
      "character": "Sledge (voice)",
      "profile": "https://image.tmdb.org/t/p/w185/keuc8jAfEM2fRce0P8FvLclwlYg.jpg"
    },
    {
      "name": "Al Michaels",
      "character": "Sparky Michaels (voice)",
      "profile": "https://image.tmdb.org/t/p/w185/bEY2GdyNicSrLtXBx0hgbiLDubd.jpg"
    },
    {
      "name": "Tommy Lasorda",
      "character": "Lucky Lasorda (voice)",
      "profile": "https://image.tmdb.org/t/p/w185/zo8qDLXu81vMp2MROJrD2ZCLpqL.jpg"
    },
    {
      "name": "Bob Uecker",
      "character": "Trixie Uecker (voice)",
      "profile": "https://image.tmdb.org/t/p/w185/pup4tVgT5qxed76BtKU3WtrQbch.jpg"
    }
  ],
  "trailer_key": "sSfkkYgv_3o",
  "imdb_id": "tt0116552",
  "vote_average": 6.623,
  "vote_count": 530
}