{
  "tmdb_id": 29963,
  "title": "Bright Star",
  "tagline": "First love burns brightest.",
  "overview": "In 1818, high-spirited young Fanny Brawne finds herself increasingly intrigued by the handsome but aloof poet John Keats, who lives next door to her family friends the Dilkes. After reading a book of his poetry, she finds herself even more drawn to the taciturn Keats. Although he agrees to teach her about poetry, Keats cannot act on his reciprocated feelings for Fanny, since as a struggling poet he has no money to support a wife.",
  "release_date": "2009-09-18",
  "runtime": 119,
  "budget": 10000000,
  "revenue": 14374652,
  "genres": [
    "Drama",
    "Romance"
  ],
  "mpaa": "PG",
  "poster_url": "https://image.tmdb.org/t/p/w342/csN6y4nq2kaBiegHaGw0DGp4plf.jpg",
  "backdrop_url": "https://image.tmdb.org/t/p/w1280/nnyaQslEbd2ST1FAhuDyF4228mb.jpg",
  "director": "Jane Campion",
  "cast": [
    {
      "name": "Abbie Cornish",
      "character": "Fanny Brawne",
      "profile": "https://image.tmdb.org/t/p/w185/AgIA8uPnwySIbqaPjr5jEXwZbS.jpg"
    },
    {
      "name": "Ben Whishaw",
      "character": "John Keats",
      "profile": "https://image.tmdb.org/t/p/w185/e74Cz65ifeNb9zHfUTvF5rTix0d.jpg"
    },
    {
      "name": "Paul Schneider",
      "character": "Mr. Brown",
      "profile": "https://image.tmdb.org/t/p/w185/69tLX644rRr1RT9gxajsWlNrf0Y.jpg"
    },
    {
      "name": "Kerry Fox",
      "character": "Mrs. Brawne",
      "profile": "https://image.tmdb.org/t/p/w185/qTN8PjqgOdICj6egcAhJ7qXfEk1.jpg"
    },
    {
      "name": "Edie Martin",
      "character": "Toots",
      "profile": ""
    },
    {
      "name": "Thomas Brodie-Sangster",
      "character": "Samuel",
      "profile": "https://image.tmdb.org/t/p/w185/ovfgjgaE7aAXKYaemABX6pJFwRk.jpg"
    },
    {
      "name": "Claudie Blakley",
      "character": "Maria Dilke",
      "profile": "https://image.tmdb.org/t/p/w185/bUy1X1ili9Goj3AQNrBD1kd7A8q.jpg"
    },
    {
      "name": "Gerard Monaco",
      "character": "Charles Dilke",
      "profile": "https://image.tmdb.org/t/p/w185/qMSwdA3InoaA2p8kFObUb2RoL8w.jpg"
    },
    {
      "name": "Antonia Campbell-Hughes",
      "character": "Abigail",
      "profile": "https://image.tmdb.org/t/p/w185/bbX2OIYN1ZrUZKZZVnQvbIrb1zs.jpg"
    },
    {
      "name": "Samuel Roukin",
      "character": "Reynolds",
      "profile": "https://image.tmdb.org/t/p/w185/rO6MJgFD5rBBeDQABN9b0YZwg4J.jpg"
    }
  ],
  "trailer_key": "K2FkxivSuVg",
  "imdb_id": "tt0810784",
  "vote_average": 6.6,
  "vote_count": 481
}