{
  "tmdb_id": 357563,
  "title": "Welcome Back",
  "tagline": "",
  "overview": "A pair of reformed gangsters try to find a husband for their newly discovered sister, but complications arise due to mistaken identities.",
  "release_date": "2015-09-04",
  "runtime": 153,
  "budget": 0,
  "revenue": 0,
  "genres": [
    "Action",
    "Comedy"
  ],
  "mpaa": "",
  "poster_url": "https://image.tmdb.org/t/p/w342/xnRIT3ggVcJxGWylKw85n6pteLp.jpg",
  "backdrop_url": "https://image.tmdb.org/t/p/w1280/vAbEoa9wyFjktWgDmu8t7ycaL9J.jpg",
  "director": "Anees Bazmee",
  "cast": [
    {
      "name": "John Abraham",
      "character": "Ajju Bhai / Ajay",
      "profile": "https://image.tmdb.org/t/p/w185/9Ur8Ki6dSEQVS0YgjDzFKxt1WmG.jpg"
    },
    {
      "name": "Shruti Haasan",
      "character": "Ranjana Shetty",
      "profile": "https://image.tmdb.org/t/p/w185/1zYJuSccSA45VVBdgozpRcL99Rd.jpg"
    },
    {
      "name": "Anil Kapoor",
      "character": "Sagar 'Majnu' Pandey",
      "profile": "https://image.tmdb.org/t/p/w185/6RcrXGFzO50Tazqc8tbDlzYKvTd.jpg"
    },
    {
      "name": "Nana Patekar",
      "character": "Uday Shankar Shetty",
      "profile": "https://image.tmdb.org/t/p/w185/gnhcslE2k2pgZK9xi1XFNZvZiEs.jpg"
    },
    {
      "name": "Paresh Rawal",
      "character": "Dr. Ghunghroo",
      "profile": "https://image.tmdb.org/t/p/w185/haRliZNMm04QXItBGScbFh4bHSJ.jpg"
    },
    {
      "name": "Dimple Kapadia",
      "character": "Poonam",
      "profile": "https://image.tmdb.org/t/p/w185/rrISOX9TnetEAiZ5zCosTkmFdh2.jpg"
    },
    {
      "name": "Naseeruddin Shah",
      "character": "Wanted Bhai",
      "profile": "https://image.tmdb.org/t/p/w185/aVCigTGfijAnnm7I7TZbceXzPMl.jpg"
    },
    {
      "name": "Shiney Ahuja",
      "character": "Honey",
      "profile": "https://image.tmdb.org/t/p/w185/w0HPmQoxelpCLqTxhlsEMAtPn5T.jpg"
    },
    {
      "name": "Om Puri",
      "character": "Narrator (voice) (uncredited)",
      "profile": "https://image.tmdb.org/t/p/w185/3xENmjr7CA8ACRViHnjOI5jPQUt.jpg"
    },
    {
      "name": "Rajpal Yadav",
      "character": "The Tailor",
      "profile": "https://image.tmdb.org/t/p/w185/aJJAU9EPiiXRsWDuy60mXE8U6lT.jpg"
    }
  ],
  "trailer_key": null,
  "imdb_id": "tt3159708",
  "vote_average": 4.912,
  "vote_count": 74
}