{
  "tmdb_id": 4966,
  "title": "The Last Days",
  "tagline": "",
  "overview": "Romance brings two warring families together in this historical drama. As citizens fight for independence in 1810s Lithuania, Tadeusz, the son of a murderer, and Zosia, a young woman, come together for a wedding against a backdrop of changing politics, ancient traditions, and the uncertain future of a country.",
  "release_date": "1999-10-22",
  "runtime": 147,
  "budget": 3330000,
  "revenue": 0,
  "genres": [
    "Drama",
    "Romance",
    "History"
  ],
  "mpaa": "",
  "poster_url": "https://image.tmdb.org/t/p/w342/zUhFR2DQLpt8YWMvEMVTa55bIEL.jpg",
  "backdrop_url": "https://image.tmdb.org/t/p/w1280/df5iAHuH2brY9zXMeeRuL2AAE6O.jpg",
  "director": "Andrzej Wajda",
  "cast": [
    {
      "name": "Bogusław Linda",
      "character": "Jacek Soplica",
      "profile": "https://image.tmdb.org/t/p/w185/rGRBCf3M7D3dstCnBrxJQIHxoyK.jpg"
    },
    {
      "name": "Daniel Olbrychski",
      "character": "Gerwazy Rębajło",
      "profile": "https://image.tmdb.org/t/p/w185/qQwqsM7pMiTRGw18SsfKvp507GW.jpg"
    },
    {
      "name": "Grażyna Szapołowska",
      "character": "Telimena",
      "profile": "https://image.tmdb.org/t/p/w185/pjI5gFihRcpee7nWJs2CFPIrQgZ.jpg"
    },
    {
      "name": "Andrzej Seweryn",
      "character": "Judge Soplica",
      "profile": "https://image.tmdb.org/t/p/w185/uYohJvqAai28Piqa0eEs6zAeFer.jpg"
    },
    {
      "name": "Marek Kondrat",
      "character": "Count Horeszko",
      "profile": "https://image.tmdb.org/t/p/w185/xasGFwdCXkKgygkoHnXZNFGuwBy.jpg"
    },
    {
      "name": "Krzysztof Kolberger",
      "character": "Adam Mickiewicz",
      "profile": "https://image.tmdb.org/t/p/w185/xEkQfRigtf6xxYDktRcwn8DPTbI.jpg"
    },
    {
      "name": "Sergey Shakurov",
      "character": "Nikita Rykow",
      "profile": "https://image.tmdb.org/t/p/w185/A1RrAYXSyBomIy2nMHqChqPJirI.jpg"
    },
    {
      "name": "Jerzy Bińczycki",
      "character": "Maciej Królik-Rózeczka",
      "profile": "https://image.tmdb.org/t/p/w185/uCcoS2OnNzQouw5Oai6HlbY0lcC.jpg"
    },
    {
      "name": "Alicja Bachleda-Curuś",
      "character": "Zosia",
      "profile": "https://image.tmdb.org/t/p/w185/ojL25lx4zeHccDDdM6r78L5Vnxw.jpg"
    },
    {
      "name": "Michał Żebrowski",
      "character": "Tadeusz Soplica",
      "profile": "https://image.tmdb.org/t/p/w185/4qzNrGn4V17nDPF3HmJcpk0rLb2.jpg"
    }
  ],
  "trailer_key": null,
  "imdb_id": "tt0170351",
  "vote_average": 5.475,
  "vote_count": 61
}