{
  "tmdb_id": 505192,
  "title": "Shoplifters",
  "tagline": "Sometimes you choose your family.",
  "overview": "In the outskirts of Tokyo, a poor but close-knit group living on the fringes of society survives through shoplifting and odd jobs. When Osamu and his son take in a neglected young girl, their already fragile existence begins to unravel. As the family grows attached to her, buried secrets surface, forcing them to confront the true meaning of love, belonging, and what makes a family.",
  "release_date": "2018-06-02",
  "runtime": 120,
  "budget": 0,
  "revenue": 0,
  "genres": [
    "Drama",
    "Crime",
    "Thriller"
  ],
  "mpaa": "R",
  "poster_url": "https://image.tmdb.org/t/p/w342/4nfRUOv3LX5zLn98WS1WqVBk9E9.jpg",
  "backdrop_url": "https://image.tmdb.org/t/p/w1280/k49RhOmaKfoybjR3vBSaOJrIGmc.jpg",
  "director": "Hirokazu Kore-eda",
  "cast": [
    {
      "name": "Lily Franky",
      "character": "Osamu Shibata",
      "profile": "https://image.tmdb.org/t/p/w185/2MIG7VSbgekrvqUpChs931NLp6B.jpg"
    },
    {
      "name": "Sakura Ando",
      "character": "Nobuyo Shibata",
      "profile": "https://image.tmdb.org/t/p/w185/k2R2ryEFEuUe2f3Dsd5yH8aRdqV.jpg"
    },
    {
      "name": "Mayu Matsuoka",
      "character": "Aki Shibata",
      "profile": "https://image.tmdb.org/t/p/w185/f7Pn68PjbhbsgwdAcQ7mxpkAYPJ.jpg"
    },
    {
      "name": "Kairi Jo",
      "character": "Shota Shibata",
      "profile": "https://image.tmdb.org/t/p/w185/asekPbtKNWY4hptwL027Xi9xZY1.jpg"
    },
    {
      "name": "Miyu Sasaki",
      "character": "Yuri",
      "profile": "https://image.tmdb.org/t/p/w185/v9ZDsXzkQ3R4N8MVcLKiWlpvanx.jpg"
    },
    {
      "name": "Kirin Kiki",
      "character": "Hatsue Shibata",
      "profile": "https://image.tmdb.org/t/p/w185/7ndJHln7nWzrCMlSaBBAz9UjiuB.jpg"
    },
    {
      "name": "Sosuke Ikematsu",
      "character": "4 Ban-san",
      "profile": "https://image.tmdb.org/t/p/w185/mNhgUAKfHdKQXhbhbAhKcRUHy30.jpg"
    },
    {
      "name": "Naoto Ogata",
      "character": "Yuzuru Shibata",
      "profile": "https://image.tmdb.org/t/p/w185/9vAzFrvZQORqxHK9flS9cRIhOMb.jpg"
    },
    {
      "name": "Yōko Moriguchi",
      "character": "Yoko Shibata",
      "profile": "https://image.tmdb.org/t/p/w185/2npiaHIqeRojOw7QqKE9lTMjFFw.jpg"
    },
    {
      "name": "Yuki Yamada",
      "character": "Yasu Hojo",
      "profile": "https://image.tmdb.org/t/p/w185/1oRe8UYddBYzyqAjlSwMTIFgg4K.jpg"
    }
  ],
  "trailer_key": "wuaoRzuVqI0",
  "imdb_id": "tt8075192",
  "vote_average": 7.841,
  "vote_count": 2280
}