{
  "tmdb_id": 63144,
  "title": "Page One: Inside the New York Times",
  "tagline": "This year, the biggest story is their own.",
  "overview": "Unprecedented access to the New York Times newsroom yields a complex view of the transformation of a media landscape fraught with both peril and opportunity.",
  "release_date": "2011-04-29",
  "runtime": 88,
  "budget": 0,
  "revenue": 429766,
  "genres": [
    "Documentary"
  ],
  "mpaa": "R",
  "poster_url": "https://image.tmdb.org/t/p/w342/rFob85bcxUb31YwTWBOYF6Gol8m.jpg",
  "backdrop_url": "https://image.tmdb.org/t/p/w1280/tfnJAQMHkunBYKcJwGkagIqyjOC.jpg",
  "director": "Andrew Rossi",
  "cast": [
    {
      "name": "David Carr",
      "character": "Self",
      "profile": ""
    },
    {
      "name": "Brian Stelter",
      "character": "Self",
      "profile": ""
    },
    {
      "name": "Bruce Headlam",
      "character": "Self",
      "profile": ""
    },
    {
      "name": "Richard Perez-Pena",
      "character": "Self",
      "profile": ""
    },
    {
      "name": "Sarah Ellison",
      "character": "Self",
      "profile": "https://image.tmdb.org/t/p/w185/xf2rpdzp4Ncje16zbGn9qoa9ZsH.jpg"
    },
    {
      "name": "Larry Ingrassia",
      "character": "Self",
      "profile": ""
    },
    {
      "name": "Dennis Crowley",
      "character": "Self",
      "profile": ""
    },
    {
      "name": "Evan Williams",
      "character": "Self",
      "profile": "https://image.tmdb.org/t/p/w185/iZ0DLzMXD6zjVnWVTaJLw3GmoHm.jpg"
    },
    {
      "name": "Paul Steiger",
      "character": "Self",
      "profile": ""
    },
    {
      "name": "Clay Shirky",
      "character": "Self",
      "profile": ""
    }
  ],
  "trailer_key": "JLct9jNrFuo",
  "imdb_id": "tt1787777",
  "vote_average": 6.9,
  "vote_count": 65
}