{
  "tmdb_id": 698128,
  "title": "Dual",
  "tagline": "The only thing that can stop you is you.",
  "overview": "A terminally ill woman opts for a cloning procedure to ease her loss on her friends and family. When she makes a miraculous recovery, her attempts to have her clone decommissioned fail and lead to a court-mandated duel to the death.",
  "release_date": "2022-03-18",
  "runtime": 95,
  "budget": 4500000,
  "revenue": 0,
  "genres": [
    "Science Fiction",
    "Comedy",
    "Drama"
  ],
  "mpaa": "R",
  "poster_url": "https://image.tmdb.org/t/p/w342/wDEse2TQRiyfhdlusSXBdkDOQRj.jpg",
  "backdrop_url": "https://image.tmdb.org/t/p/w1280/3QrD6F2MKooZhlnMqrzknzcQp92.jpg",
  "director": "Riley Stearns",
  "cast": [
    {
      "name": "Karen Gillan",
      "character": "Sarah",
      "profile": "https://image.tmdb.org/t/p/w185/kFLXcFdok3ShDxylr3WNreQphQm.jpg"
    },
    {
      "name": "Aaron Paul",
      "character": "Trent",
      "profile": "https://image.tmdb.org/t/p/w185/8Ac9uuoYwZoYVAIJfRLzzLsGGJn.jpg"
    },
    {
      "name": "Beulah Koale",
      "character": "Peter",
      "profile": "https://image.tmdb.org/t/p/w185/payzbNPVpNXgX5SBtWBLNWfdfuS.jpg"
    },
    {
      "name": "Theo James",
      "character": "Robert Michaels",
      "profile": "https://image.tmdb.org/t/p/w185/lSC4cMhcQeCjPFkK6qCjSGDSeR3.jpg"
    },
    {
      "name": "Elina Jackson",
      "character": "Official with Flags",
      "profile": "https://image.tmdb.org/t/p/w185/qghHLfTVfmlLSgBFmxvW2wLQADZ.jpg"
    },
    {
      "name": "Maija Paunio",
      "character": "Sarah's Mother",
      "profile": "https://image.tmdb.org/t/p/w185/ibcRB75cGpt249FGdzfNsIGzZVz.jpg"
    },
    {
      "name": "Rea Lest-Liik",
      "character": "Emergency Room Receptionist",
      "profile": "https://image.tmdb.org/t/p/w185/88v8qO7ltD55fGlvYhgymrBqafC.jpg"
    },
    {
      "name": "Sanna-June Hyde",
      "character": "Gastroenterologist",
      "profile": "https://image.tmdb.org/t/p/w185/A1i1zrXx6QEhCVE4lzrvqlwoLJy.jpg"
    },
    {
      "name": "Kris Gummerus",
      "character": "Tom",
      "profile": "https://image.tmdb.org/t/p/w185/pMwaax13Q3xDzSe2KYFajMc1XQO.jpg"
    },
    {
      "name": "Nico Siekkinen",
      "character": "Two Identical Handsome Men",
      "profile": ""
    }
  ],
  "trailer_key": "OX7L8pFWO0k",
  "imdb_id": "tt9005184",
  "vote_average": 5.962,
  "vote_count": 378
}