{
  "tmdb_id": 701387,
  "title": "Bugonia",
  "tagline": "Of all the abductions, this one is different.",
  "overview": "Two conspiracy obsessed young men kidnap the high-powered CEO of a major company, convinced that she is an alien intent on destroying planet Earth.",
  "release_date": "2025-10-23",
  "runtime": 119,
  "budget": 50000000,
  "revenue": 40796580,
  "genres": [
    "Science Fiction",
    "Thriller",
    "Comedy"
  ],
  "mpaa": "R",
  "poster_url": "https://image.tmdb.org/t/p/w342/oxgsAQDAAxA92mFGYCZllgWkH9J.jpg",
  "backdrop_url": "https://image.tmdb.org/t/p/w1280/tN3pTxkQoP96wtaEahYuRVdUWb2.jpg",
  "director": "Yorgos Lanthimos",
  "cast": [
    {
      "name": "Emma Stone",
      "character": "Michelle",
      "profile": "https://image.tmdb.org/t/p/w185/cZ8a3QvAnj2cgcgVL6g4XaqPzpL.jpg"
    },
    {
      "name": "Jesse Plemons",
      "character": "Teddy",
      "profile": "https://image.tmdb.org/t/p/w185/og4I51GsuwohdPgoELOHVMMqMre.jpg"
    },
    {
      "name": "Aidan Delbis",
      "character": "Don",
      "profile": "https://image.tmdb.org/t/p/w185/k9xKpm9cVryO3dgdsyxvC46FyBW.jpg"
    },
    {
      "name": "Stavros Halkias",
      "character": "Casey",
      "profile": "https://image.tmdb.org/t/p/w185/9QB7YGMk6O7hRgGWvK0OimTVzl7.jpg"
    },
    {
      "name": "Alicia Silverstone",
      "character": "Sandy",
      "profile": "https://image.tmdb.org/t/p/w185/pyxqkP4i0ubVdoRe5hoiiiwkHkb.jpg"
    },
    {
      "name": "J. Carmen Galindez Barrera",
      "character": "Ricky / Security Guard",
      "profile": "https://image.tmdb.org/t/p/w185/2ktCkWgexsBTbh0UFsbdKoHX4D1.jpg"
    },
    {
      "name": "Marc T. Lewis",
      "character": "Tony",
      "profile": "https://image.tmdb.org/t/p/w185/rrwyDxRMfnPnRvFEX1uuvdRq9WQ.jpg"
    },
    {
      "name": "Vanessa Eng",
      "character": "Corey",
      "profile": "https://image.tmdb.org/t/p/w185/3HYU97U1wKR9byRBvu5SVpvifeH.jpg"
    },
    {
      "name": "Cedric Dumornay",
      "character": "Chris",
      "profile": "https://image.tmdb.org/t/p/w185/t8YtnWbZV8To3PGLE6xHUB6o8Sm.jpg"
    },
    {
      "name": "Momma Cherri",
      "character": "Tina",
      "profile": ""
    }
  ],
  "trailer_key": "7VBigr-JHB0",
  "imdb_id": "tt12300742",
  "vote_average": 7.358,
  "vote_count": 1802
}