{
  "tmdb_id": 987686,
  "title": "A Family Affair",
  "tagline": "A motherf*&‍#er of a love story.",
  "overview": "The only thing worse than being the assistant to a high-maintenance movie star who doesn't take you seriously? Finding out he's smitten with your mom.",
  "release_date": "2024-06-27",
  "runtime": 114,
  "budget": 0,
  "revenue": 0,
  "genres": [
    "Romance",
    "Comedy"
  ],
  "mpaa": "PG-13",
  "poster_url": "https://image.tmdb.org/t/p/w342/l0CaVyqnTsWwNd4hWsrLNEk1Wjd.jpg",
  "backdrop_url": "https://image.tmdb.org/t/p/w1280/ngLxW9WqQAkTCBTcjOSt2Pnz5qZ.jpg",
  "director": "Richard LaGravenese",
  "cast": [
    {
      "name": "Nicole Kidman",
      "character": "Brooke Harwood",
      "profile": "https://image.tmdb.org/t/p/w185/lfW2cDigTcvuoe4k6UfCdGVE1R6.jpg"
    },
    {
      "name": "Zac Efron",
      "character": "Chris Cole",
      "profile": "https://image.tmdb.org/t/p/w185/6oXNHv7gAyXXYFpF943pKRsTtqQ.jpg"
    },
    {
      "name": "Joey King",
      "character": "Zara Ford",
      "profile": "https://image.tmdb.org/t/p/w185/94c69mPYSK9jFsAEu0OKB7Qs684.jpg"
    },
    {
      "name": "Kathy Bates",
      "character": "Leila Ford",
      "profile": "https://image.tmdb.org/t/p/w185/qZRTzTjV4OC1Ii9a0n8QBS9zMOd.jpg"
    },
    {
      "name": "Liza Koshy",
      "character": "Eugenie",
      "profile": "https://image.tmdb.org/t/p/w185/pPu4TYkuNGmPEykWzFwCz55pAWB.jpg"
    },
    {
      "name": "Wes Jetton",
      "character": "Emmanuel",
      "profile": "https://image.tmdb.org/t/p/w185/dWFKapIUgIt8tDBGjSShRWZR0iO.jpg"
    },
    {
      "name": "Ian Gregg",
      "character": "Malcolm",
      "profile": "https://image.tmdb.org/t/p/w185/5IiSdwRrc79FfJvRnscmKmaW5UP.jpg"
    },
    {
      "name": "Sarah Baskin",
      "character": "French Director",
      "profile": "https://image.tmdb.org/t/p/w185/liAplTvz1Q3UkVQxKgaF09w1mcT.jpg"
    },
    {
      "name": "Zele Avradopoulos",
      "character": "Mila",
      "profile": "https://image.tmdb.org/t/p/w185/kLNxsFxEtVU5xC1GHhmmIizQ1jT.jpg"
    },
    {
      "name": "Vince Pisani",
      "character": "Jesse",
      "profile": "https://image.tmdb.org/t/p/w185/auCC2e7IKC146MDvO4k8tPXMKaZ.jpg"
    }
  ],
  "trailer_key": "Ytc2eifpiuQ",
  "imdb_id": "tt21051906",
  "vote_average": 5.739,
  "vote_count": 719
}