{
  "_source": "tmdb-enrich",
  "title": "Corpse Bride",
  "tmdb_id": 3933,
  "release_date": "2005-09-12",
  "runtime": 77,
  "genres": [
    "Romance",
    "Fantasy",
    "Animation"
  ],
  "mpaa": "PG",
  "budget": 40000000,
  "revenue": 118133252,
  "poster_url": "https://image.tmdb.org/t/p/w342/isb2Qow76GpqYmsSyfdMfsYAjts.jpg",
  "backdrop_url": "https://image.tmdb.org/t/p/w1280/v23fWgJUEt8EMmvn19btIacxP8E.jpg",
  "tagline": "There's been a grave misunderstanding.",
  "overview": "In a 19th-century European village, a young man about to be married is whisked away to the underworld and wed to a mysterious corpse bride, while his real bride waits bereft in the land of the living."
}