{
  "_source": "tmdb-enrich",
  "title": "Fly Me to the Moon",
  "tmdb_id": 956842,
  "release_date": "2024-07-10",
  "runtime": 132,
  "genres": [
    "Romance",
    "Comedy"
  ],
  "mpaa": "PG-13",
  "budget": 100000000,
  "revenue": 42260534,
  "poster_url": "https://image.tmdb.org/t/p/w342/lb0XDH6LbkYwzbHTqjsUNZTLXMS.jpg",
  "backdrop_url": "https://image.tmdb.org/t/p/w1280/4ItXEyVPj6wb9AdhsltcqYE6f5f.jpg",
  "tagline": "Will they make history... or fake it?",
  "overview": "Sparks fly in all directions as marketing maven Kelly Jones, brought in to fix NASA's public image, wreaks havoc on Apollo 11 launch director Cole Davis' already difficult task of putting a man on the moon. When the White House deems the mission too important to fail, Jones is directed to stage a fake moon landing as backup, and the countdown truly begins."
}