{
  "_source": "tmdb-enrich",
  "title": "Friends with Kids",
  "tmdb_id": 80038,
  "release_date": "2012-03-09",
  "runtime": 100,
  "genres": [
    "Comedy",
    "Drama",
    "Romance"
  ],
  "mpaa": "R",
  "budget": 0,
  "revenue": 12186625,
  "poster_url": "https://image.tmdb.org/t/p/w342/cA6putv2ND8snBBa0t9WhlW1TfG.jpg",
  "backdrop_url": "https://image.tmdb.org/t/p/w1280/4uXIXErELMjnGX3lnEhChEhfnnn.jpg",
  "tagline": "Love. Happiness. Kids. Pick two.",
  "overview": "In the wake of their friends' marriages and eventual offspring, longtime pals Julie and Jason decide to have a child together without becoming a couple. By becoming \"time-share\" parents, they reason, they can experience the joys of parenthood without significantly curbing their personal freedom. However, when Julie and Jason both become involved with others, they discover that they secretly harbor romantic feelings for each other."
}