{
  "_source": "tmdb-enrich",
  "title": "Identity",
  "tmdb_id": 2832,
  "release_date": "2003-04-25",
  "runtime": 90,
  "genres": [
    "Mystery",
    "Thriller"
  ],
  "mpaa": "R",
  "budget": 28000000,
  "revenue": 90259536,
  "poster_url": "https://image.tmdb.org/t/p/w342/sYgimsiBywqVwJI8H4sETke8m7v.jpg",
  "backdrop_url": "https://image.tmdb.org/t/p/w1280/bjKTwVrzX2cflxRhvAlqvOdloTG.jpg",
  "tagline": "The secret lies within.",
  "overview": "Complete strangers stranded at a remote desert motel during a raging storm soon find themselves the target of a deranged murderer. As their numbers thin out, the travelers begin to turn on each other, as each tries to figure out who the killer is."
}