{
  "_source": "tmdb-enrich",
  "title": "Junction 48",
  "tmdb_id": 382751,
  "release_date": "2016-04-15",
  "runtime": 97,
  "genres": [
    "Drama",
    "Action",
    "Crime"
  ],
  "mpaa": "",
  "budget": 0,
  "revenue": 0,
  "poster_url": "https://image.tmdb.org/t/p/w342/xoCa0btnQ5Y5MKZ0gAmeWQGmMo8.jpg",
  "backdrop_url": "https://image.tmdb.org/t/p/w1280/yHsl5iMiQ1FNG1cygye53SxaMGy.jpg",
  "tagline": "",
  "overview": "Set against a backdrop of the Israeli-Palestinian conflict, Palestinian rapper Kareem and his singer girlfriend Manar struggle, love and make music in their crime-ridden ghetto and Tel Aviv's hip-hop club scene."
}