{
  "_source": "tmdb-enrich",
  "title": "Kicked in the Head",
  "tmdb_id": 56651,
  "release_date": "1997-09-26",
  "runtime": 89,
  "genres": [
    "Comedy",
    "Crime",
    "Drama",
    "Romance"
  ],
  "mpaa": "",
  "budget": 4000000,
  "revenue": 102739,
  "poster_url": "https://image.tmdb.org/t/p/w342/jJVtdeWddiarPpWgSnEBXEJAsz4.jpg",
  "backdrop_url": "https://image.tmdb.org/t/p/w1280/27K96VQqxNRHbaJSHBgirCz4u64.jpg",
  "tagline": "A satirical love story.",
  "overview": "When Redmond finds himself out of home and job, his life becomes a series of unpredictable escapades - from dodging gunfire after his uncle makes him deliver a highly suspicious package to pursuing a moody stewardess he thinks has come to save him. Soon Redmond begins to suspect his road of mishap might actually be the path to the truth he has been seeking all along."
}