{
  "_source": "tmdb-enrich",
  "title": "Lemon",
  "tmdb_id": 428585,
  "release_date": "2017-01-22",
  "runtime": 83,
  "genres": [
    "Drama",
    "Comedy"
  ],
  "mpaa": "",
  "budget": 0,
  "revenue": 29258,
  "poster_url": "https://image.tmdb.org/t/p/w342/cZWjfUKuqufDjp3C9ufI8DLAxH7.jpg",
  "backdrop_url": "https://image.tmdb.org/t/p/w1280/9Qyr7lcDOU7jdDYOfrOaFVwo8Ep.jpg",
  "tagline": "",
  "overview": "Isaac has seen better days. His acting career is tanking, his blind girlfriend of 10 years plans to leave him, and his own family singles him out as a constant disappointment. Even as he takes a chance on new romance, he struggles to define his place in a world that has seemingly turned against him."
}