{
  "_source": "tmdb-enrich",
  "title": "Monk in Pieces",
  "tmdb_id": 1418515,
  "release_date": "2025-07-25",
  "runtime": 94,
  "genres": [
    "Documentary",
    "Music"
  ],
  "mpaa": "",
  "budget": 0,
  "revenue": 0,
  "poster_url": "https://image.tmdb.org/t/p/w342/rDD5MqFljMeWBu36riwFFtoEvQu.jpg",
  "backdrop_url": "https://image.tmdb.org/t/p/w1280/tPFXjvkisHHSTfQI9o2wWhcDm46.jpg",
  "tagline": "\"She among all of us was--and still is--the uniquely gifted one.\" -Phillip Glass",
  "overview": "Visionary composer and performer Meredith Monk overcame hostile critics to become one of the great artists of her time. In her seventh decade of creativity, she ponders how such singular work can continue without her."
}