{
  "_source": "tmdb-enrich",
  "title": "The True Story of the Big Red One",
  "tmdb_id": 1272624,
  "release_date": "1998-03-01",
  "runtime": 94,
  "genres": [
    "History"
  ],
  "mpaa": "",
  "budget": 0,
  "revenue": 0,
  "poster_url": "",
  "backdrop_url": "",
  "tagline": "war, military, history",
  "overview": "THE TRUE STORY OF THE BIG RED ONE is pitting Hollywood fiction against historical fact, where we'll examine the reality behind Samuel Fuller's great war movie \"The Big Red One\". Based upon Fuller's own World War II experiences, the film starred Lee Marvin as the intrepid sergeant of special infantry squadron in various campaigns of the war.  Learn the dramatic story of the illustrious First Division of the U.S. Army - called the Big Red One because of the red numeral \"1\" on its uniforms' shoulders - from it's organization in 1917 through the present day."
}