{
  "_source": "tmdb-enrich",
  "title": "The Eel",
  "tmdb_id": 20506,
  "release_date": "1997-05-12",
  "runtime": 117,
  "genres": [
    "Drama",
    "Crime"
  ],
  "mpaa": "",
  "budget": 0,
  "revenue": 0,
  "poster_url": "https://image.tmdb.org/t/p/w342/3TEzcwdF3DPeO8uSPmCfBBUhgNp.jpg",
  "backdrop_url": "https://image.tmdb.org/t/p/w1280/2yYrBdhPzsrHQlNqswFa90y6bZu.jpg",
  "tagline": "",
  "overview": "A businessman kills his adulterous wife and is sent to prison. After his release, he opens a barbershop and meets new people, talking  to almost no one except for an eel he befriended while in prison."
}